{
  "reading": "Community Beekeeping and Outreach: Fostering Sustainable Development Through Apiculture\\n\\nIntroduction\\n\\nCommunity beekeeping and outreach programs have emerged as powerful tools for sustainable development, environmental conservation, and economic empowerment in many regions around the world. By harnessing the natural benefits of bees and integrating apiculture into community initiatives, these programs offer a multifaceted approach to addressing various social, economic, and ecological challenges. This article explores the concept of community beekeeping, its various models, and the significant impact it can have on local communities.\\n\\nModels of Community-Based Beekeeping Projects\\n\\nSeveral models have been developed to implement community beekeeping projects effectively. [BLANK_1] are one such model, where a group of individuals collectively own and operate beehives, sharing resources, knowledge, and profits. This approach allows for economies of scale and provides a support network for beekeepers.\\n\\nCommunity [BLANK_2] represent another model, where a centralized location houses multiple hives managed by community members. This setup is particularly beneficial in urban or peri-urban areas where individual land for beekeeping may be limited.\\n\\nSchool-based beekeeping programs integrate apiculture into educational curricula, providing students with hands-on learning experiences while also benefiting the local ecosystem. These programs often serve as a gateway to environmental education and can inspire future generations of beekeepers and conservationists.\\n\\nWomen's beekeeping initiatives have gained traction in many developing countries as a means of economic empowerment. These projects provide women with skills, resources, and market access, allowing them to generate income and enhance their social status within their communities.\\n\\nIntegrating Beekeeping into Community Development\\n\\nThe versatility of beekeeping allows it to be seamlessly integrated into various [BLANK_3] initiatives. For instance, beekeeping can be linked to existing agricultural projects, enhancing crop pollination and diversifying farm income. In coffee-growing regions, for example, beehives placed near coffee plantations can significantly increase yields through improved pollination while providing honey as an additional product.\\n\\nBeekeeping also serves as an excellent tool for environmental education. Through hands-on experience with bees, community members gain a deeper understanding of ecosystem interdependence, biodiversity, and the importance of pollinator conservation. This knowledge can lead to more [BLANK_4] land management practices and increased environmental stewardship.\\n\\nMoreover, community beekeeping creates diverse economic opportunities. Beyond honey production, communities can develop value-added products such as beeswax candles, cosmetics, and medicinal products. These activities can stimulate local entrepreneurship and create jobs, particularly in rural areas with limited economic prospects.\\n\\n[BLANK_5] and Education in Community Beekeeping\\n\\nEffective outreach and education are crucial for the success of community beekeeping initiatives. Hands-on demonstrations and practical examples are essential teaching methods, allowing novice beekeepers to gain confidence in handling bees and managing hives. Visual aids, such as posters or videos, can help convey complex concepts, especially in areas with varying literacy levels.\\n\\nCultural considerations play a significant role in beekeeping education. In many societies, bees hold cultural or spiritual significance, and educational approaches must be sensitive to these beliefs. By incorporating traditional knowledge and practices into modern beekeeping techniques, outreach programs can gain greater acceptance and effectiveness.\\n\\n[BLANK_6] is another critical aspect of community beekeeping outreach. By developing local expertise through training programs and workshops, communities can become self-sufficient in their beekeeping practices and even serve as knowledge hubs for surrounding areas.\\n\\nConclusion\\n\\nCommunity beekeeping and outreach programs offer a [BLANK_7] and multifaceted approach to community development. By combining economic opportunities with environmental conservation and education, these initiatives can create lasting positive impacts on local communities. As the world grapples with challenges such as food security, biodiversity loss, and rural poverty, community beekeeping stands out as a promising solution that harnesses the power of nature to build resilient and thriving communities.",
  "vocabulary": {
    "[BLANK_1]": "Cooperatives",
    "[BLANK_2]": "apiaries",
    "[BLANK_3]": "community development",
    "[BLANK_4]": "sustainable",
    "[BLANK_5]": "Outreach",
    "[BLANK_6]": "Capacity building",
    "[BLANK_7]": "sustainable",
    "[BLANK_8]": "stakeholder",
    "[BLANK_9]": "demonstration hive",
    "[BLANK_10]": "extension service"
  }
}