{
  "title": "Breath and Energy Awareness in Nei Gong",
  "questions": [
    {
      "question": "What is the primary muscle used in diaphragmatic breathing?",
      "choices": [
        "Intercostal muscles",
        "Abdominal muscles",
        "Diaphragm",
        "Pectoralis major"
      ],
      "answer": "Diaphragm"
    },
    {
      "question": "Where is the lower Dantian located?",
      "choices": [
        "In the chest",
        "At the base of the spine",
        "Approximately 3 finger-widths below the navel",
        "In the throat"
      ],
      "answer": "Approximately 3 finger-widths below the navel"
    },
    {
      "question": "What is Qi in the context of Nei Gong?",
      "choices": [
        "A type of breathing exercise",
        "The fundamental life energy or vital force",
        "A meditation technique",
        "The Chinese word for diaphragm"
      ],
      "answer": "The fundamental life energy or vital force"
    },
    {
      "question": "How many main Dantians are there in Nei Gong practice?",
      "choices": [
        "One",
        "Two",
        "Three",
        "Four"
      ],
      "answer": "Three"
    },
    {
      "question": "What is the goal of observing natural breath in Nei Gong practice?",
      "choices": [
        "To control the breath",
        "To increase heart rate",
        "To increase awareness",
        "To hold the breath for longer periods"
      ],
      "answer": "To increase awareness"
    },
    {
      "question": "Which of the following is NOT a characteristic of Qi?",
      "choices": [
        "It can be cultivated",
        "It is visible to the naked eye",
        "It flows through all living things",
        "It influences physical and mental health"
      ],
      "answer": "It is visible to the naked eye"
    },
    {
      "question": "What is the relationship between breath and Qi in Nei Gong?",
      "choices": [
        "They are unrelated concepts",
        "Breath is a vehicle for Qi",
        "Qi controls the breath",
        "Breath eliminates Qi"
      ],
      "answer": "Breath is a vehicle for Qi"
    },
    {
      "question": "Which of the following is a benefit of focusing on the lower Dantian?",
      "choices": [
        "Increased flexibility",
        "Improved eyesight",
        "Enhanced memory",
        "Grounding and centering"
      ],
      "answer": "Grounding and centering"
    },
    {
      "question": "What happens to the diaphragm during inhalation?",
      "choices": [
        "It relaxes and domes",
        "It contracts and flattens",
        "It moves upward",
        "It remains stationary"
      ],
      "answer": "It contracts and flattens"
    },
    {
      "question": "In Nei Gong practice, what is believed to happen during exhalation?",
      "choices": [
        "Fresh Qi is drawn in",
        "Stale Qi is released",
        "Qi is stored in the Dantian",
        "Qi circulation stops"
      ],
      "answer": "Stale Qi is released"
    },
    {
      "question": "What is the recommended duration for the daily breath observation practice?",
      "choices": [
        "1-2 minutes",
        "5-10 minutes",
        "20-30 minutes",
        "1 hour"
      ],
      "answer": "5-10 minutes"
    },
    {
      "question": "What is the purpose of the Qi sensing exercise with palms?",
      "choices": [
        "To strengthen hand muscles",
        "To improve circulation",
        "To sense the subtle energy between the hands",
        "To practice hand-eye coordination"
      ],
      "answer": "To sense the subtle energy between the hands"
    },
    {
      "question": "What is another name for the lower Dantian?",
      "choices": [
        "Third eye",
        "Crown chakra",
        "Sea of Qi",
        "Heart center"
      ],
      "answer": "Sea of Qi"
    },
    {
      "question": "Which of the following is NOT a topic covered in Learning Unit 2?",
      "choices": [
        "Natural breathing observation",
        "Locating the lower Dantian energy center",
        "Advanced Qi circulation techniques",
        "Introducing the concept of Qi"
      ],
      "answer": "Advanced Qi circulation techniques"
    },
    {
      "question": "What type of clothing is recommended for Nei Gong practice?",
      "choices": [
        "Tight-fitting exercise clothes",
        "Comfortable, loose-fitting clothing",
        "Traditional Chinese robes",
        "No specific recommendation"
      ],
      "answer": "Comfortable, loose-fitting clothing"
    },
    {
      "question": "What is the purpose of keeping a journal in Nei Gong practice?",
      "choices": [
        "To improve writing skills",
        "To record experiences and observations",
        "To plan future exercises",
        "To communicate with the instructor"
      ],
      "answer": "To record experiences and observations"
    },
    {
      "question": "What is the recommended visualization for the Dantian awareness exercise?",
      "choices": [
        "A bright light",
        "A flowing river",
        "Warmth or a soft glow",
        "A spinning wheel"
      ],
      "answer": "Warmth or a soft glow"
    },
    {
      "question": "In the context of Nei Gong, what does 'Yi' refer to?",
      "choices": [
        "A type of breathing technique",
        "The lower Dantian",
        "Intention or focused awareness",
        "A meditation posture"
      ],
      "answer": "Intention or focused awareness"
    },
    {
      "question": "What is the primary focus of the breathing meditation practice in this unit?",
      "choices": [
        "Rapid breathing",
        "Breath holding",
        "Natural breath observation",
        "Forced exhalation"
      ],
      "answer": "Natural breath observation"
    },
    {
      "question": "Which of the following is a suggested adaptation for Nei Gong practice in Timor-Leste?",
      "choices": [
        "Practicing only indoors",
        "Wearing traditional Timorese clothing",
        "Adjusting practices for the tropical climate",
        "Using only Chinese language instructions"
      ],
      "answer": "Adjusting practices for the tropical climate"
    },
    {
      "question": "What is the purpose of inviting respected elders in the Nei Gong program?",
      "choices": [
        "To teach advanced techniques",
        "To share traditional Timorese wellness practices",
        "To provide translation services",
        "To demonstrate Chinese martial arts"
      ],
      "answer": "To share traditional Timorese wellness practices"
    },
    {
      "question": "What is the recommended surface for floor exercises in Nei Gong practice?",
      "choices": [
        "Hardwood floor",
        "Carpeted surface",
        "Yoga mat or padded surface",
        "Bare ground"
      ],
      "answer": "Yoga mat or padded surface"
    },
    {
      "question": "Which of the following is NOT mentioned as a benefit of regular breathing exercises?",
      "choices": [
        "Improved oxygen uptake",
        "Lower blood pressure",
        "Increased muscle mass",
        "Reduced muscle tension"
      ],
      "answer": "Increased muscle mass"
    },
    {
      "question": "What is the purpose of rubbing palms together in the Qi sensing exercise?",
      "choices": [
        "To warm up the hands",
        "To stimulate Qi flow",
        "To improve circulation",
        "All of the above"
      ],
      "answer": "All of the above"
    },
    {
      "question": "How is the concept of Qi related to Traditional Chinese Medicine?",
      "choices": [
        "It is unrelated to TCM",
        "It is a fundamental concept in TCM",
        "It is only used in acupuncture",
        "It is a modern addition to TCM"
      ],
      "answer": "It is a fundamental concept in TCM"
    },
    {
      "question": "What is the significance of the lower Dantian in Nei Gong practice for beginners?",
      "choices": [
        "It is the easiest to locate",
        "It is the most important for beginners",
        "It is only used by advanced practitioners",
        "It has no special significance for beginners"
      ],
      "answer": "It is the most important for beginners"
    },
    {
      "question": "Which of the following is a characteristic of natural breathing in Nei Gong?",
      "choices": [
        "Shallow chest breathing",
        "Forced abdominal movement",
        "Gentle expansion of the lower abdomen on inhalation",
        "Holding the breath for long periods"
      ],
      "answer": "Gentle expansion of the lower abdomen on inhalation"
    },
    {
      "question": "What is the recommended frequency for the breath awareness journaling exercise?",
      "choices": [
        "Once a week",
        "Twice a week",
        "Every other day",
        "Daily"
      ],
      "answer": "Daily"
    },
    {
      "question": "Which of the following is NOT mentioned as a topic to observe in natural breathing?",
      "choices": [
        "Rhythm of breath",
        "Depth of breath",
        "Color of breath",
        "Areas of movement"
      ],
      "answer": "Color of breath"
    },
    {
      "question": "What is the primary goal of the Dantian awareness exercise?",
      "choices": [
        "To increase abdominal muscle strength",
        "To improve digestion",
        "To cultivate and store Qi",
        "To enhance flexibility"
      ],
      "answer": "To cultivate and store Qi"
    }
  ]
}