{
  "title": "Archetypes of the Collective Unconscious in Timorese Society",
  "questions": [
    {
      "question": "Who introduced the concept of archetypes and the collective unconscious?",
      "choices": [
        "Sigmund Freud",
        "Carl Jung",
        "B.F. Skinner",
        "Erik Erikson"
      ],
      "answer": "Carl Jung"
    },
    {
      "question": "What does Jung's collective unconscious contain?",
      "choices": [
        "Personal memories",
        "Cultural stereotypes",
        "Inherited patterns of thought and experience",
        "Conscious beliefs"
      ],
      "answer": "Inherited patterns of thought and experience"
    },
    {
      "question": "Which animal is central to Timorese mythology and represents the Hero archetype?",
      "choices": [
        "Eagle",
        "Lion",
        "Crocodile",
        "Tiger"
      ],
      "answer": "Crocodile"
    },
    {
      "question": "What is the name for the sacred house in Timorese culture?",
      "choices": [
        "Uma lulik",
        "Tais",
        "Banyan",
        "Mandala"
      ],
      "answer": "Uma lulik"
    },
    {
      "question": "Which archetype does the uma lulik primarily represent?",
      "choices": [
        "The Trickster",
        "The Great Mother",
        "The Hero",
        "The Shadow"
      ],
      "answer": "The Great Mother"
    },
    {
      "question": "What is tais in Timorese culture?",
      "choices": [
        "A traditional dance",
        "A woven cloth",
        "A sacred animal",
        "A type of food"
      ],
      "answer": "A woven cloth"
    },
    {
      "question": "Which archetype is often represented in the patterns of tais?",
      "choices": [
        "The Hero",
        "The Trickster",
        "The Mandala",
        "The Animus"
      ],
      "answer": "The Mandala"
    },
    {
      "question": "What do the anima and animus archetypes represent?",
      "choices": [
        "Good and evil",
        "Past and future",
        "Feminine and masculine aspects of the psyche",
        "Life and death"
      ],
      "answer": "Feminine and masculine aspects of the psyche"
    },
    {
      "question": "Which archetype is often embodied in clever and mischievous characters in Timorese folklore?",
      "choices": [
        "The Wise Old Man",
        "The Great Mother",
        "The Hero",
        "The Trickster"
      ],
      "answer": "The Trickster"
    },
    {
      "question": "What does the Shadow archetype represent in Jungian psychology?",
      "choices": [
        "Unconscious desires",
        "Darker aspects of the human psyche",
        "Cultural taboos",
        "Childhood memories"
      ],
      "answer": "Darker aspects of the human psyche"
    },
    {
      "question": "How does the crocodile relate to Timorese identity?",
      "choices": [
        "It's a common pet",
        "It's believed to have formed the island of Timor",
        "It's a symbol of evil",
        "It represents foreign influence"
      ],
      "answer": "It's believed to have formed the island of Timor"
    },
    {
      "question": "What role does the uma lulik play in Timorese communities?",
      "choices": [
        "It's a marketplace",
        "It's a government building",
        "It's a physical and spiritual center",
        "It's a school"
      ],
      "answer": "It's a physical and spiritual center"
    },
    {
      "question": "What aspect of tais production embodies the Creator archetype?",
      "choices": [
        "Wearing the cloth",
        "Selling the cloth",
        "The process of weaving",
        "Dyeing the threads"
      ],
      "answer": "The process of weaving"
    },
    {
      "question": "How do Timorese social structures reflect the anima and animus archetypes?",
      "choices": [
        "Through equal rights for all",
        "Through specific roles and responsibilities for men and women",
        "Through the absence of gender distinctions",
        "Through matriarchal dominance"
      ],
      "answer": "Through specific roles and responsibilities for men and women"
    },
    {
      "question": "What purpose do stories of ancestral heroes serve in Timorese culture?",
      "choices": [
        "They provide entertainment only",
        "They reflect universal themes while incorporating Timorese elements",
        "They discourage cultural pride",
        "They promote Western values"
      ],
      "answer": "They reflect universal themes while incorporating Timorese elements"
    },
    {
      "question": "How is the Shadow archetype expressed in Timorese beliefs?",
      "choices": [
        "Through optimistic folklore",
        "Through beliefs about malevolent spirits and taboos",
        "Through political structures",
        "Through agricultural practices"
      ],
      "answer": "Through beliefs about malevolent spirits and taboos"
    },
    {
      "question": "What does the study of Timorese archetypes reveal about the collective unconscious?",
      "choices": [
        "It's identical across all cultures",
        "It's completely unique to Timor-Leste",
        "It shows both commonalities and unique cultural adaptations",
        "It proves the collective unconscious doesn't exist"
      ],
      "answer": "It shows both commonalities and unique cultural adaptations"
    },
    {
      "question": "Which of the following is NOT a key component of Jung's theory of the collective unconscious?",
      "choices": [
        "Archetypes",
        "Universal patterns",
        "Inherited experiences",
        "Personal memories"
      ],
      "answer": "Personal memories"
    },
    {
      "question": "What does the Banyan tree represent in Timorese culture?",
      "choices": [
        "The connection between earth and sky",
        "The cycle of life and death",
        "The conflict between good and evil",
        "The passage of time"
      ],
      "answer": "The connection between earth and sky"
    },
    {
      "question": "Which archetype does the Warrior figure in Timorese culture primarily represent?",
      "choices": [
        "The Trickster",
        "The Hero",
        "The Great Mother",
        "The Wise Old Man"
      ],
      "answer": "The Hero"
    },
    {
      "question": "How does understanding archetypes in Timorese culture contribute to cross-cultural communication?",
      "choices": [
        "It highlights cultural differences only",
        "It provides a common framework for understanding human experiences",
        "It proves the superiority of Timorese culture",
        "It shows that cultures cannot be compared"
      ],
      "answer": "It provides a common framework for understanding human experiences"
    },
    {
      "question": "What is the significance of the crocodile myth in Timorese culture?",
      "choices": [
        "It warns about the dangers of swimming",
        "It explains the origin of the island and its people",
        "It promotes crocodile conservation",
        "It describes ancient hunting practices"
      ],
      "answer": "It explains the origin of the island and its people"
    },
    {
      "question": "How do tais patterns serve as a form of communication?",
      "choices": [
        "They contain written messages",
        "They use Morse code",
        "They convey archetypal themes non-verbally",
        "They produce sounds when woven"
      ],
      "answer": "They convey archetypal themes non-verbally"
    },
    {
      "question": "What role does the warrior archetype play in shaping Timorese identity?",
      "choices": [
        "It promotes pacifism",
        "It encourages isolationism",
        "It reflects the struggle for independence",
        "It discourages cultural pride"
      ],
      "answer": "It reflects the struggle for independence"
    },
    {
      "question": "How does the uma lulik embody the Wise Old Man archetype?",
      "choices": [
        "It houses a council of elders",
        "It represents wisdom and tradition",
        "It is always built on the highest point in a village",
        "It is painted with images of old men"
      ],
      "answer": "It represents wisdom and tradition"
    },
    {
      "question": "What is the relationship between archetypes and cultural symbols in Timorese society?",
      "choices": [
        "Archetypes and cultural symbols are unrelated",
        "Cultural symbols often represent archetypes",
        "Archetypes always override cultural symbols",
        "Cultural symbols replace archetypes entirely"
      ],
      "answer": "Cultural symbols often represent archetypes"
    },
    {
      "question": "How does the concept of the collective unconscious help explain similarities in myths across cultures?",
      "choices": [
        "It suggests all cultures have the same history",
        "It proposes a shared repository of human experiences",
        "It proves that all myths originated in Timor-Leste",
        "It shows that myths are scientifically accurate"
      ],
      "answer": "It proposes a shared repository of human experiences"
    },
    {
      "question": "What is the primary function of archetypes according to Jung?",
      "choices": [
        "To create cultural differences",
        "To shape understanding of the world and one's place in it",
        "To prevent psychological growth",
        "To enforce social norms"
      ],
      "answer": "To shape understanding of the world and one's place in it"
    },
    {
      "question": "How do Timorese archetypes differ from their Western counterparts?",
      "choices": [
        "They are completely unrelated",
        "They share core essence but have unique cultural manifestations",
        "They are identical in all aspects",
        "Timorese culture has no archetypes"
      ],
      "answer": "They share core essence but have unique cultural manifestations"
    },
    {
      "question": "What insight does the study of Timorese archetypes provide about cultural identity?",
      "choices": [
        "Cultural identity is solely determined by geography",
        "Archetypes play no role in cultural identity",
        "Cultural identity is shaped by both universal patterns and unique adaptations",
        "All cultures have identical archetypes and thus identical identities"
      ],
      "answer": "Cultural identity is shaped by both universal patterns and unique adaptations"
    }
  ]
}