{
  "title": "Tara Mantras and Visualization Techniques",
  "questions": [
    {
      "question": "What is the ten-syllable Tara mantra?",
      "choices": [
        "OM MANI PADME HUM",
        "OM TARE TUTTARE TURE SOHA",
        "OM AH HUM VAJRA GURU PADMA SIDDHI HUM",
        "OM BENZA SATTO HUM"
      ],
      "answer": "OM TARE TUTTARE TURE SOHA"
    },
    {
      "question": "What does the syllable 'TARE' in the Tara mantra signify?",
      "choices": [
        "Granting all wishes",
        "Protection from inner fears",
        "Protection from worldly dangers",
        "The primordial sound of the universe"
      ],
      "answer": "Protection from worldly dangers"
    },
    {
      "question": "What color is Green Tara typically depicted as?",
      "choices": [
        "Blue",
        "White",
        "Red",
        "Green"
      ],
      "answer": "Green"
    },
    {
      "question": "What posture is Green Tara usually seated in?",
      "choices": [
        "Full lotus",
        "Lalitasana (royal ease)",
        "Standing",
        "Bhumisparsha mudra"
      ],
      "answer": "Lalitasana (royal ease)"
    },
    {
      "question": "What does Tara's right foot extended symbolize?",
      "choices": [
        "Her connection to the earth",
        "Her readiness to step into action",
        "Her transcendence of worldly concerns",
        "Her ability to grant wishes"
      ],
      "answer": "Her readiness to step into action"
    },
    {
      "question": "What flower does Tara typically hold in her left hand?",
      "choices": [
        "Lotus",
        "Rose",
        "Utpala",
        "Chrysanthemum"
      ],
      "answer": "Utpala"
    },
    {
      "question": "What mudra (hand gesture) does Tara's right hand usually display?",
      "choices": [
        "Dharmachakra mudra",
        "Abhaya mudra",
        "Varada mudra",
        "Vitarka mudra"
      ],
      "answer": "Varada mudra"
    },
    {
      "question": "What does the name 'Tara' mean?",
      "choices": [
        "Goddess",
        "Protector",
        "Star or She who ferries across",
        "Enlightened One"
      ],
      "answer": "Star or She who ferries across"
    },
    {
      "question": "How many eyes is Tara typically depicted with?",
      "choices": [
        "Two",
        "Three",
        "Four",
        "One"
      ],
      "answer": "Three"
    },
    {
      "question": "What does Tara's third eye represent?",
      "choices": [
        "Her ability to see past, present, and future",
        "Her enlightenment",
        "Her compassion",
        "Her connection to other deities"
      ],
      "answer": "Her ability to see past, present, and future"
    },
    {
      "question": "What is the purpose of visualization in Tara practice?",
      "choices": [
        "To improve artistic skills",
        "To cultivate single-pointed concentration and develop Tara's qualities",
        "To induce lucid dreaming",
        "To communicate with other practitioners"
      ],
      "answer": "To cultivate single-pointed concentration and develop Tara's qualities"
    },
    {
      "question": "What is the significance of the green color in Green Tara's iconography?",
      "choices": [
        "It represents nature",
        "It symbolizes enlightened activity",
        "It signifies her connection to healing",
        "It is purely decorative"
      ],
      "answer": "It symbolizes enlightened activity"
    },
    {
      "question": "In the story of Tara's origin, from whose tear was she born?",
      "choices": [
        "Buddha Shakyamuni",
        "Avalokiteshvara",
        "Amitabha",
        "Vajrapani"
      ],
      "answer": "Avalokiteshvara"
    },
    {
      "question": "What is the recommended number of times to recite the Tara mantra daily in the homework assignment?",
      "choices": [
        "21",
        "108",
        "1000",
        "3"
      ],
      "answer": "108"
    },
    {
      "question": "What is a mala used for in Tara practice?",
      "choices": [
        "As an offering to Tara",
        "To count mantra recitations",
        "As a decorative necklace",
        "To ward off evil spirits"
      ],
      "answer": "To count mantra recitations"
    },
    {
      "question": "What is the main benefit associated with Tara practice?",
      "choices": [
        "Material wealth",
        "Swift protection and liberation from fears",
        "Improved physical health",
        "Enhanced psychic abilities"
      ],
      "answer": "Swift protection and liberation from fears"
    },
    {
      "question": "In the visualization practice, where is the practitioner instructed to imagine Tara appearing?",
      "choices": [
        "Above their head",
        "In front of them",
        "In their heart center",
        "In the sky"
      ],
      "answer": "In their heart center"
    },
    {
      "question": "What does 'SOHA' mean at the end of the Tara mantra?",
      "choices": [
        "Amen",
        "May the blessing be firmly rooted",
        "Thank you",
        "Farewell"
      ],
      "answer": "May the blessing be firmly rooted"
    },
    {
      "question": "What is the purpose of incorporating local materials in creating a Tara altar?",
      "choices": [
        "To save money",
        "To make the altar more durable",
        "To adapt the practice to Timorese cultural context",
        "To impress the teacher"
      ],
      "answer": "To adapt the practice to Timorese cultural context"
    },
    {
      "question": "What is the significance of Tara's left leg being folded in the meditation posture?",
      "choices": [
        "It represents her human aspect",
        "It symbolizes her mastery over worldly attachments",
        "It is a sign of respect",
        "It has no specific meaning"
      ],
      "answer": "It symbolizes her mastery over worldly attachments"
    },
    {
      "question": "What is the main purpose of the reflective journal entry assignment?",
      "choices": [
        "To improve writing skills",
        "To document the number of mantras recited",
        "To reflect on personal experiences with Tara practice",
        "To critique the teaching methods"
      ],
      "answer": "To reflect on personal experiences with Tara practice"
    },
    {
      "question": "What is the significance of the lotus throne Tara sits on?",
      "choices": [
        "It represents her royal status",
        "It symbolizes purity and enlightenment",
        "It is simply a comfortable seat",
        "It represents the earth element"
      ],
      "answer": "It symbolizes purity and enlightenment"
    },
    {
      "question": "What is the purpose of studying Tara iconography from Southeast Asian art?",
      "choices": [
        "To critique artistic styles",
        "To understand how Tara practice has been adapted to different cultures",
        "To learn drawing techniques",
        "To prepare for a career in art history"
      ],
      "answer": "To understand how Tara practice has been adapted to different cultures"
    },
    {
      "question": "What is the recommended way to begin a Tara visualization practice?",
      "choices": [
        "With physical exercise",
        "By chanting loudly",
        "With breath awareness",
        "By studying scripture"
      ],
      "answer": "With breath awareness"
    },
    {
      "question": "What is the Anjali Mudra used for in Tara practice?",
      "choices": [
        "To invoke protection",
        "To show reverence and devotion",
        "To symbolize teaching",
        "To represent enlightenment"
      ],
      "answer": "To show reverence and devotion"
    },
    {
      "question": "What is the primary goal of combining mantra recitation with visualization in Tara practice?",
      "choices": [
        "To improve memory",
        "To create a more immersive and transformative experience",
        "To make the practice more challenging",
        "To attract more followers"
      ],
      "answer": "To create a more immersive and transformative experience"
    },
    {
      "question": "According to the module, how does Tara visualization help in spiritual development?",
      "choices": [
        "By improving imagination skills",
        "By providing entertainment during meditation",
        "By helping to dissolve the boundary between self and other",
        "By inducing trance states"
      ],
      "answer": "By helping to dissolve the boundary between self and other"
    },
    {
      "question": "What is the significance of the green light emanating from Tara in the visualization practice?",
      "choices": [
        "It represents jealousy to be overcome",
        "It is a sign of illness",
        "It symbolizes Tara's blessings and protection",
        "It has no specific meaning"
      ],
      "answer": "It symbolizes Tara's blessings and protection"
    },
    {
      "question": "What is the recommended duration for the guided Tara visualization in the lesson plan?",
      "choices": [
        "5 minutes",
        "10 minutes",
        "20 minutes",
        "1 hour"
      ],
      "answer": "20 minutes"
    },
    {
      "question": "What is the purpose of the group project to create a Tara altar?",
      "choices": [
        "To decorate the classroom",
        "To practice teamwork skills",
        "To apply learned concepts and adapt them to local context",
        "To compete for the best design"
      ],
      "answer": "To apply learned concepts and adapt them to local context"
    }
  ]
}